clavata_sdk/__init__.py
clavata_sdk/src/__init__.py
clavata_sdk/src/api.py
clavata_sdk/src/errs.py
clavata_sdk/src/grpc_status.py
clavata_sdk/src/models.py
clavata_sdk/src/version.py
protobufs/clavata/gateway/v1/analytics_pb2.py
protobufs/clavata/gateway/v1/analytics_pb2.pyi
protobufs/clavata/gateway/v1/analytics_pb2_grpc.py
protobufs/clavata/gateway/v1/api_tokens_pb2.py
protobufs/clavata/gateway/v1/api_tokens_pb2.pyi
protobufs/clavata/gateway/v1/api_tokens_pb2_grpc.py
protobufs/clavata/gateway/v1/authproxy_pb2.py
protobufs/clavata/gateway/v1/authproxy_pb2.pyi
protobufs/clavata/gateway/v1/authproxy_pb2_grpc.py
protobufs/clavata/gateway/v1/content_pb2.py
protobufs/clavata/gateway/v1/content_pb2.pyi
protobufs/clavata/gateway/v1/content_pb2_grpc.py
protobufs/clavata/gateway/v1/content_private_pb2.py
protobufs/clavata/gateway/v1/content_private_pb2.pyi
protobufs/clavata/gateway/v1/content_private_pb2_grpc.py
protobufs/clavata/gateway/v1/datasets_pb2.py
protobufs/clavata/gateway/v1/datasets_pb2.pyi
protobufs/clavata/gateway/v1/datasets_pb2_grpc.py
protobufs/clavata/gateway/v1/deployments_pb2.py
protobufs/clavata/gateway/v1/deployments_pb2.pyi
protobufs/clavata/gateway/v1/deployments_pb2_grpc.py
protobufs/clavata/gateway/v1/errs_pb2.py
protobufs/clavata/gateway/v1/errs_pb2.pyi
protobufs/clavata/gateway/v1/errs_pb2_grpc.py
protobufs/clavata/gateway/v1/gateway_pb2.py
protobufs/clavata/gateway/v1/gateway_pb2.pyi
protobufs/clavata/gateway/v1/gateway_pb2_grpc.py
protobufs/clavata/gateway/v1/invites_pb2.py
protobufs/clavata/gateway/v1/invites_pb2.pyi
protobufs/clavata/gateway/v1/invites_pb2_grpc.py
protobufs/clavata/gateway/v1/limits_pb2.py
protobufs/clavata/gateway/v1/limits_pb2.pyi
protobufs/clavata/gateway/v1/limits_pb2_grpc.py
protobufs/clavata/gateway/v1/policies_pb2.py
protobufs/clavata/gateway/v1/policies_pb2.pyi
protobufs/clavata/gateway/v1/policies_pb2_grpc.py
protobufs/clavata/gateway/v1/policies_private_pb2.py
protobufs/clavata/gateway/v1/policies_private_pb2.pyi
clavata_sdk-1.0.2.dist-info/METADATA
clavata_sdk-1.0.2.dist-info/WHEEL
clavata_sdk-1.0.2.dist-info/RECORD
