Metadata-Version: 2.4
Name: clavata-sdk
Version: 1.0.2
Summary: Clavata SDK for Python
Author: Brett Levenson
Author-email: brett@clavata.ai
Requires-Python: >=3.10,<4.0
Classifier: Programming Language :: Python :: 3
Classifier: Programming Language :: Python :: 3.10
Classifier: Programming Language :: Python :: 3.11
Classifier: Programming Language :: Python :: 3.12
Classifier: Programming Language :: Python :: 3.13
Classifier: Programming Language :: Python :: 3.14
Requires-Dist: grpcio (>=1.62.0,<2.0.0)
Requires-Dist: protobuf (>=5.29.5,<6.0.0)
Requires-Dist: typing-extensions (>=4.12.0)
